yoomoney_payment/__init__.py
yoomoney_payment/forms.py
yoomoney_payment/urls.py
yoomoney_payment/views.py
yoomoney_payment/commerce/__init__.py
yoomoney_payment/commerce/checkout.py
yoomoney_payment/commerce/conf.py
yoomoney_payment/commerce/dummy.py
yoomoney_payment/templates/yoomoney_payment.html
yoomoney_payment/tests/__init__.py
yoomoney_payment/tests/mixins.py
yoomoney_payment/tests/test_service.py
yoomoney_payment/tests/test_views.py
yoomoney_payment-2.0.0.dist-info/METADATA
yoomoney_payment-2.0.0.dist-info/WHEEL
yoomoney_payment-2.0.0.dist-info/top_level.txt
yoomoney_payment-2.0.0.dist-info/RECORD
