Metadata-Version: 2.4
Name: yoomoney-payment
Version: 2.0.0
Summary: A library to provide payment gateway for YooMoney Payment
Home-page: https://bitbucket.org/akinonteam/yoo-payment/
Author: Akinon
Author-email: dev@akinon.com
Requires-Dist: Django<4.3,>=2.2.9
Requires-Dist: requests
Requires-Dist: djangorestframework<4,>=3.14.0
Dynamic: author
Dynamic: author-email
Dynamic: description
Dynamic: description-content-type
Dynamic: home-page
Dynamic: requires-dist
Dynamic: summary
